gradio_viewer/__init__.py
gradio_viewer/viewer.py
gradio_viewer/viewer.pyi
gradio_viewer/templates/component/index.js
gradio_viewer/templates/component/style.css
gradio_viewer/templates/example/index.js
gradio_viewer/templates/example/style.css
gradio_viewer-0.0.25.dist-info/METADATA
gradio_viewer-0.0.25.dist-info/WHEEL
gradio_viewer-0.0.25.dist-info/RECORD
